openinference/instrumentation/bedrock/__init__.py
openinference/instrumentation/bedrock/_attribute_extractor.py
openinference/instrumentation/bedrock/_converse_attributes.py
openinference/instrumentation/bedrock/_converse_stream_callback.py
openinference/instrumentation/bedrock/_proxy.py
openinference/instrumentation/bedrock/_rag_wrappers.py
openinference/instrumentation/bedrock/_response_accumulator.py
openinference/instrumentation/bedrock/_trace_collector.py
openinference/instrumentation/bedrock/_wrappers.py
openinference/instrumentation/bedrock/package.py
openinference/instrumentation/bedrock/py.typed
openinference/instrumentation/bedrock/version.py
openinference/instrumentation/bedrock/__generated__/__init__.py
openinference/instrumentation/bedrock/__generated__/anthropic/__init__.py
openinference/instrumentation/bedrock/__generated__/anthropic/_types.py
openinference/instrumentation/bedrock/utils/__init__.py
openinference/instrumentation/bedrock/utils/_extract_invoke_model_attributes.py
openinference/instrumentation/bedrock/utils/json_utils.py
openinference/instrumentation/bedrock/utils/anthropic/__init__.py
openinference/instrumentation/bedrock/utils/anthropic/_attributes.py
openinference/instrumentation/bedrock/utils/anthropic/_messages.py
openinference_instrumentation_bedrock-0.1.31.dist-info/METADATA
openinference_instrumentation_bedrock-0.1.31.dist-info/WHEEL
openinference_instrumentation_bedrock-0.1.31.dist-info/entry_points.txt
openinference_instrumentation_bedrock-0.1.31.dist-info/licenses/LICENSE
openinference_instrumentation_bedrock-0.1.31.dist-info/RECORD
