Metadata-Version: 2.4
Name: openinference-instrumentation-bedrock
Version: 0.1.31
Summary: OpenInference Bedrock Instrumentation
Project-URL: Homepage, https://github.com/Arize-ai/openinference/tree/main/python/instrumentation/openinference-instrumentation-bedrock
Author-email: OpenInference Authors <oss@arize.com>
License-Expression: Apache-2.0
License-File: LICENSE
Classifier: Development Status :: 5 - Production/Stable
Classifier: Intended Audience :: Developers
Classifier: License :: OSI Approved :: Apache Software License
Classifier: Programming Language :: Python
Classifier: Programming Language :: Python :: 3
Classifier: Programming Language :: Python :: 3.9
Classifier: Programming Language :: Python :: 3.10
Classifier: Programming Language :: Python :: 3.11
Classifier: Programming Language :: Python :: 3.12
Classifier: Programming Language :: Python :: 3.13
Classifier: Programming Language :: Python :: 3.14
Requires-Python: <3.15,>=3.9
Requires-Dist: dacite>=1.8.1
Requires-Dist: openinference-instrumentation>=0.1.27
Requires-Dist: openinference-semantic-conventions>=0.1.17
Requires-Dist: opentelemetry-api
Requires-Dist: opentelemetry-instrumentation
Requires-Dist: opentelemetry-semantic-conventions
Requires-Dist: typing-extensions
Requires-Dist: wrapt
Provides-Extra: instruments
Requires-Dist: boto3>=1.38.17; extra == 'instruments'
Provides-Extra: test
Requires-Dist: anthropic>=0.47.0; extra == 'test'
Requires-Dist: boto3==1.38.17; extra == 'test'
Requires-Dist: opentelemetry-instrumentation-httpx; extra == 'test'
Requires-Dist: opentelemetry-sdk; extra == 'test'
Requires-Dist: pydantic>=2.10.6; extra == 'test'
Requires-Dist: pytest-vcr>=1.0.2; extra == 'test'
Requires-Dist: requests; extra == 'test'
Requires-Dist: types-requests; extra == 'test'
